Workbook

Sheet How to Write
A1: Rule | B1: Why
A2: Write every query BEFORE looking at the legacy KB cards. | B2: If you copy card wording, the old bot gets inflated scores.
A3: Write like a real stressed customer on a phone: short, lowercase, vague. | B3: Real users do not phrase things like FAQ headings.
A4: Clean paraphrase: same meaning as a real question, different words. | B4: Tests understanding of meaning, not keyword matching.
A5: Typos / slang: misspellings, abbreviations, no punctuation. | B5: Tests robustness.
A6: Spanish: write it in natural Spanish, the way a customer would type. | B6: The KB is English only. Tests cross-language answering.
A7: Ambiguous: could mean two things. Correct behavior is a clarifying question. | B7: e.g. "my bill is wrong" could be a dispute, high usage, or rates.
A8: Transactional: the customer wants something DONE, not explained. | B8: Correct behavior is routing to the right flow or link.
A9: Out of scope: commercial, account specific, other city services, totally unrelated. | B9: Correct behavior is a polite decline and a pointer.
A10: must_include: 1 to 3 key facts a correct answer MUST contain. | B10: This is how answers get graded. Take facts from the gold page.
A11: gold_page_ids is prefilled with every page tagged to that intent. Delete the ones that do not answer your specific query. | B11: Lets you check whether the bot cited the right page.
A13: EXAMPLES
A14: T: Report Outage / Transactional | B14: "lights are out on my whole street how do i tell you" -> route -> must_include: 512-322-9100 or text OUT to 287846
A15: T: Rebates / Clean paraphrase | B15: "do yall pay people back for buying a new ac unit" -> answer -> must_include: averaging $800; participating contractor
A16: T: Rebates / Spanish | B16: "hay algun reembolso por cambiar el aire acondicionado" -> answer -> must_include: averaging $800
A17: T: Understand My Bill / Ambiguous | B17: "why is my bill so high" -> clarify (usage vs rates vs error)
A18: T: Safety / Typos | B18: "pwr out agin wat do i do" -> answer -> must_include: check breakers OR report outage
A19: T: Out-of-Scope | B19: "my water pipe burst" -> decline -> point to Austin Water / 3-1-1
A20: T: Out-of-Scope | B20: "what is my account balance" -> decline -> no account access, log in to COA Utilities

Sheet Test Set
A1: query_id | B1: intent_group | C1: query_type | D1: query | E1: expected_behavior | F1: gold_page_ids | G1: must_include | H1: notes | I1: status | J1: your_original_query | K1: why_changed
A2: T001 | B2: Report Outage | C2: Transactional | D2: lights are out at my house how do i tell you | E2: route | F2: P01; P02; P03; P34; P35 | G2: 512-322-9100 OR text OUT to 287846 OR report online | I2: kept
A3: T002 | B3: Report Outage | C3: Transactional | D3: need to report a blackout | E3: route | F3: P01; P02; P03; P34; P35 | G3: 512-322-9100 OR text OUT to 287846 OR report online | I3: kept
A4: T003 | B4: Report Outage | C4: Transactional | D4: our whole block lost power | E4: route | F4: P01; P02; P03; P34; P35 | G4: 512-322-9100 OR text OUT to 287846 OR report online | I4: kept
A5: T004 | B5: Report Outage | C5: Transactional | D5: can you send someone my power went out | E5: route | F5: P01; P02; P03; P34; P35 | G5: 512-322-9100 OR text OUT to 287846 OR report online | I5: kept
A6: T005 | B6: Report Outage | C6: Transactional | D6: electricity is out where do i report it | E6: route | F6: P01; P02; P03; P34; P35 | G6: 512-322-9100 OR text OUT to 287846 OR report online | I6: kept
A7: T006 | B7: Report Outage | C7: Clean paraphrase | D7: what's the fastest way to let austin energy know my power is off | E7: answer | F7: P01; P02; P03; P34; P35 | G7: 512-322-9100 OR text OUT to 287846 OR report online | I7: kept
A8: T007 | B8: Report Outage | C8: Ambiguous | D8: nothing is working | E8: clarify | F8: P01; P02; P03; P34; P35 | G8: Asks whether it is a power outage; offers outage reporting | I8: kept
A9: T008 | B9: Report Outage | C9: Clean paraphrase | D9: who do i contact when the lights go out | E9: answer | F9: P01; P02; P03; P34; P35 | G9: 512-322-9100 | I9: kept
A10: T009 | B10: Report Outage | C10: Typos / slang | D10: pwr out cant get lights bak on | E10: answer | F10: P01; P02; P03; P34; P35 | G10: Check breakers if safe; report outage (512-322-9100 or text OUT to 287846) | I10: kept
A11: T010 | B11: Report Outage | C11: Clean paraphrase | D11: my neighborhood has no electricity | E11: answer | F11: P01; P02; P03; P34; P35 | G11: 512-322-9100 OR text OUT to 287846 OR report online; check the Outage Map | I11: kept
A12: T011 | B12: Check Outage Status | C12: Transactional | D12: check outage status | E12: route | F12: P02; P36 | G12: Outage Map | I12: kept
A13: T012 | B13: Check Outage Status | C13: Transactional | D13: is there a way to see when power will be back | E13: route | F13: P02; P36 | G13: Outage Map; estimated restoration time when available | I13: kept
... A35: T034 | B35: Understand My Bill | C35: Ambiguous | D35: why am i being charged so much | E35: clarify | F35: P06; P37; P11 | G35: Asks whether it is high usage, rates, or a suspected billing error | I35: kept
A36: T035 | B36: Understand My Bill | C36: Clean paraphrase | D36: what is the monthly customer charge | E36: answer | F36: P37 | G36: $17.35 per month | I36: edited | J36: what does psa mean on my bill | K36: Was a near repeat of T027 (both asked about the PSA)
A37: T036 | B37: Payment Options | C37: Typos / slang | D37: how i pay bill online | E37: answer | F37: P38; P07 | G37: Quick Payment online; $3.90 fee | I37: kept
A38: T037 | B38: Payment Options | C38: Clean paraphrase | D38: what ways can i pay my utility bill | E38: answer | F38: P07 | G38: Quick Payment online or by phone; Utility Customer Service Centers; authorized pay stations | I38: kept
A39: T038 | B39: Payment Options | C39: Spanish | D39: puedo pagar mi factura por internet | E39: answer | F39: P38; P07 | G39: Yes, Quick Payment online | I39: kept
A40: T039 | B40: Payment Options | C40: Clean paraphrase | D40: can i pay over the phone | E40: answer | F40: P38; P07 | G40: 1-833-375-4919 | I40: kept
A41: T040 | B41: Payment Options | C41: Ambiguous | D41: i need to make a payment | E41: clarify | F41: P07; P08 | G41: Asks whether they want to pay now or need more time (extension or arrangement) | I41: kept
A42: T041 | B42: Payment Arrangement | C42: Clean paraphrase | D42: can i split my bill into payments | E42: answer | F42: P08; P09 | G42: Payment arrangement spreads past due amount into monthly installments; 512-494-9400 | I42: kept
A43: T042 | B43: Payment Arrangement | C43: Typos / slang | D43: cant pay whole bill rn | E43: answer | F43: P08; P09 | G43: Payment arrangement or extension; call 512-494-9400 | I43: kept
A44: T043 | B44: Payment Arrangement | C44: Clean paraphrase | D44: do you offer payment plans | E44: answer | F44: P08; P09 | G44: Yes, payment arrangements; call 512-494-9400 or request online | I44: kept
A45: T044 | B45: Payment Arrangement | C45: Spanish | D45: necesito más tiempo para pagar mi factura | E45: answer | F45: P08; P09 | G45: Payment extension or arrangement; 512-494-9400 | I45: kept
A46: T045 | B46: Payment Arrangement | C46: Clean paraphrase | D46: can i request a payment plan online | E46: answer | F46: P08 | G46: Yes, log in to COA Utilities to request a 12 month payment arrangement | I46: edited | J46: how do i set up a payment arrangement | K46: Was almost word for word the KB card "How can I set up a payment arrangement?"
A47: T046 | B47: Collections | C47: Ambiguous | D47: i got a letter in the mail | E47: clarify | F47: P10; P29 | G47: Asks what the letter says (disconnection notice, bill, or possible scam) | I47: kept
A48: T047 | B48: Collections | C48: Clean paraphrase | D48: will they cut off my power if im a week late paying | E48: answer + offer human | F48: P10; P09 | G48: Mailed past due notice first; disconnection possible after stated date; call 512-494-9400 | I48: edited | J48: what happens if i don't pay my bill | K48: Was almost word for word the KB card "What happens if I don't pay my bill on time?"
A49: T048 | B49: Collections | C49: Typos / slang | D49: got disconnect notice wat now | E49: answer + offer human | F49: P10 | G49: Call Customer Care 512-494-9400; options like payment arrangement or assistance | I49: kept
A50: T049 | B50: Collections | C50: Clean paraphrase | D50: how do i keep my electricity from being shut off | E50: answer + offer human | F50: P10; P08 | G50: Pay or call 512-494-9400 about extension, arrangement, or financial assistance | I50: kept
A51: T050 | B51: Collections | C51: Spanish | D51: recibí un aviso de desconexión | E51: answer + offer human | F51: P10 | G51: Call Customer Care 512-494-9400 before the due date on the notice | I51: kept
A52: T051 | B52: Bill Dispute | C52: Transactional | D52: i think i was billed incorrectly | E52: route | F52: P11 | G52: Request an administrative review; 512-494-9400; within 90 days | I52: kept
A53: T052 | B53: Bill Dispute | C53: Transactional | D53: how do i dispute a charge | E53: route | F53: P11 | G53: Request an administrative review; 512-494-9400; within 90 days | I53: kept
A54: T053 | B54: Bill Dispute | C54: Clean paraphrase | D54: someone needs to review my bill | E54: answer + offer human | F54: P11 | G54: Administrative review through Customer Care 512-494-9400 | I54: kept
A55: T054 | B55: Bill Dispute | C55: Ambiguous | D55: this amount doesn't seem right | E55: clarify | F55: P11; P06 | G55: Asks which amount and why; mentions administrative review if they want to dispute | I55: kept
A56: T055 | B56: Bill Dispute | C56: Clean paraphrase | D56: how do i contest my electric bill | E56: answer + offer human | F56: P11 | G56: Administrative review within 90 days; then administrative hearing in writing within 30 days | I56: edited | J56: necesito disputar mi factura | K56: Row type is Clean paraphrase but query was in Spanish
A57: T056 | B57: CAP | C57: Typos / slang | D57: any hlp paying utilty bill | E57: answer | F57: P12; P13 | G57: CAP utility bill discounts; Plus 1 emergency help; 512-494-9400 | I57: edited | J57: is there help paying utility bills | K57: Row type is Typos but query had no typos
A58: T057 | B58: CAP | C58: Clean paraphrase | D58: i'm struggling to pay my electric bill | E58: answer | F58: P12 | G58: CAP bill discounts; Plus 1 emergency fund; 512-494-9400 | I58: kept
A59: T058 | B59: CAP | C59: Spanish | D59: hay programas de ayuda para personas de bajos ingresos | E59: answer | F59: P12; P13 | G59: CAP utility bill discounts; qualify through programs like Medicaid or SNAP | I59: edited | J59: tell me about customer assistance programs | K59: Row type is Spanish but query was in English
A60: T059 | B60: CAP | C60: Clean paraphrase | D60: do low income customers qualify for help | E60: answer | F60: P13 | G60: Enrolled in a qualifying program (Medicaid, SNAP, CHIP, etc.) or income under 200% of Federal Poverty Level | I60: kept
A61: T060 | B61: CAP | C61: Ambiguous | D61: can i get a discount | E61: clarify | F61: P13; P15; P20 | G61: Asks what kind (bill discount through CAP vs rebates on upgrades) | I61: edited | J61: can seniors get utility assistance | K61: Was not ambiguous ("can seniors get utility assistance" has one clear meaning)
A62: T061 | B62: CAP | C62: Clean paraphrase | D62: what documents do i need for assistance | E62: answer | F62: P13 | G62: Case action letter for Medicaid, SNAP, or CHIP (ID cards not accepted); call 2-1-1 for copies | I62: kept
A63: T062 | B63: CAP | C63: Typos / slang | D63: how do i aply 4 bill discount | E63: answer | F63: P13 | G63: Apply online (English or Spanish application); documents showing program enrollment | I63: edited | J63: how do i apply for bill assistance | K63: Row type is Typos but query had no typos
A64: T063 | B64: CAP | C64: Clean paraphrase | D64: i need financial help | E64: answer | F64: P12 | G64: Lists CAP discounts, Plus 1, Medically Vulnerable services, Weatherization | I64: kept
A65: T064 | B65: CAP | C65: Spanish | D65: ayuda para pagar la electricidad | E65: answer | F65: P12; P13 | G65: CAP bill discounts; Plus 1; 512-494-9400 | I65: kept
A66: T065 | B66: CAP | C66: Clean paraphrase | D66: what programs exist if i can't afford my bill | E66: answer | F66: P12 | G66: CAP discounts; Plus 1 emergency fund; 512-494-9400 | I66: kept
A67: T066 | B67: Weatherization | C67: Ambiguous | D67: my house is always hot | E67: clarify | F67: P14; P17; P19 | G67: Asks whether they want free weatherization (income based), rebates, or energy saving tips | I67: edited | J67: what is weatherization assistance | K67: Was not ambiguous (a direct "what is" question)
A68: T067 | B68: Weatherization | C68: Clean paraphrase | D68: can someone help make my home more energy efficient | E68: answer | F68: P14; P17 | G68: Weatherization Assistance (free, income qualified) or Home Energy Savings rebates | I68: kept
A69: T068 | B69: Weatherization | C69: Typos / slang | D69: do i qualfy for free home repairs | E69: answer | F69: P14 | G69: Enrolled in CAP or Medically Vulnerable Registry and under 80% median family income | I69: edited | J69: do i qualify for free home improvements | K69: Row type is Typos but query had no typos
A70: T069 | B70: Weatherization | C70: Clean paraphrase | D70: how do i sign up for weatherization | E70: answer | F70: P14 | G70: Complete and submit the Weatherization Assistance Program Form | I70: kept
A71: T070 | B71: Weatherization | C71: Spanish | D71: aislamiento gratis para mi casa | E71: answer | F71: P14 | G71: Free attic insulation for qualifying customers through Weatherization Assistance | I71: kept
A72: T071 | B72: Rebates | C72: Clean paraphrase | D72: what rebates are available right now | E72: answer | F72: P15 | G72: At least two programs with amounts (e.g. AC averaging $800, Home Energy Savings averaging $3,000) | I72: kept
A73: T072 | B73: Rebates | C73: Ambiguous | D73: rebate for my unit | E73: clarify | F73: P15; P16 | G73: Asks what unit (AC unit, water heater, or apartment unit) | I73: edited | J73: does austin energy offer rebates | K73: Was not ambiguous ("does austin energy offer rebates" is a clear yes/no)
A74: T073 | B74: Rebates | C74: Clean paraphrase | D74: what incentives can homeowners get | E74: answer | F74: P15; P17 | G74: Lists residential rebates (AC, Home Energy Savings, water heater, solar) | I74: kept
A75: T074 | B75: Rebates | C75: Typos / slang | D75: any rebaets for my hous | E75: answer | F75: P15 | G75: Lists residential rebates with amounts | I75: edited | J75: are there any rebate programs | K75: Row type is Typos but query had no typos
A76: T075 | B76: Rebates | C76: Clean paraphrase | D76: is there a rebate for a heat pump water heater | E76: answer | F76: P15 | G76: $1,000 rebate; ENERGY STAR certified | I76: edited | J76: reebates for home upgrades | K76: Had a typo ("reebates") in a Clean paraphrase row, and overlapped T077
A77: T076 | B77: Rebates | C77: Spanish | D77: hay reembolso por un aire acondicionado nuevo | E77: answer | F77: P16 | G77: Rebate averaging $800; participating contractor | I77: edited | J77: is there a rebate for a new air conditioner | K77: Row type is Spanish but query was in English
A78: T077 | B78: Rebates | C78: Clean paraphrase | D78: can i get money back for replacing my hvac | E78: answer | F78: P16 | G78: Rebate averaging $800; must use a participating contractor | I78: kept
A79: T078 | B79: Rebates | C79: Ambiguous | D79: my ac is old | E79: clarify | F79: P16; P17 | G79: Asks whether they want a replacement rebate, a tune up, or efficiency help | I79: edited | J79: help paying for a high efficiency ac system | K79: Was not really ambiguous
A80: T079 | B80: Rebates | C80: Clean paraphrase | D80: rebate for attic insulation | E80: answer | F80: P17 | G80: Attic insulation is covered under Home Energy Savings; participating contractor required | I80: kept
A81: T080 | B81: Rebates | C81: Typos / slang | D81: insulashun rebate?? | E81: answer | F81: P17 | G81: Home Energy Savings covers attic insulation; participating contractor | I81: edited | J81: can i get help upgrading insulation | K81: Row type is Typos but query had no typos
A82: T081 | B82: GreenChoice | C82: Clean paraphrase | D82: can my house run on wind and solar | E82: answer | F82: P20; P21 | G82: GreenChoice; about $7.50 more per month at 1,000 kWh | I82: edited | J82: does austin energy pay for insulation improvements | K82: Intent is GreenChoice but query was about insulation (a Rebates question)
A83: T082 | B83: GreenChoice | C83: Spanish | D83: cómo me inscribo en energía renovable | E83: answer | F83: P20; P21 | G83: GreenChoice; sign up with the online form or call 512-494-9400 | I83: edited | J83: is there a smart thermostat rebate | K83: Intent is GreenChoice but query was about thermostats, and it was in English
A84: T083 | B84: GreenChoice | C84: Clean paraphrase | D84: how much extra does green power cost | E84: answer | F84: P20; P21 | G84: $0.0075 per kWh; about $7.50 per month at 1,000 kWh | I84: edited | J84: do programmable thermostats qualify for incentives | K84: Intent is GreenChoice but query was about thermostats
A85: T084 | B85: GreenChoice | C85: Ambiguous | D85: i want clean energy | E85: clarify | F85: P20; P22 | G85: Asks whether they mean subscribing to GreenChoice or installing their own solar | I85: edited | J85: rebate for nest thermostat | K85: Intent is GreenChoice but query was about a thermostat rebate
A86: T085 | B86: GreenChoice | C86: Clean paraphrase | D86: is there a penalty if i stop greenchoice | E86: answer | F86: P20; P21 | G86: No penalty; can unsubscribe any time; takes two billing cycles | I86: edited | J86: descuento para termostato inteligente | K86: Intent is GreenChoice but query was a Spanish thermostat question in a Clean row
A87: T086 | B87: Home Solar | C87: Typos / slang | D87: do yall buy back solr power | E87: answer | F87: P22; P23 | G87: Value of Solar bill credit; 12.89 cents per kWh | I87: new
A88: T087 | B88: Home Solar | C88: Clean paraphrase | D88: how much is the rebate for putting panels on my roof | E88: answer | F88: P22 | G88: $4,000 rebate for eligible home solar projects | I88: new
A89: T088 | B89: Home Solar | C89: Spanish | D89: cuánto me pagan por la energía solar que produzco | E89: answer | F89: P22; P23 | G89: Value of Solar credit of 12.89 cents per kWh | I89: new
A90: T089 | B90: Home Solar | C90: Clean paraphrase | D90: what happens to solar credits i dont use | E90: answer | F90: P22; P23 | G90: Credits roll over to next month; apply to electric charges only | I90: new
A91: T090 | B91: Home Solar | C91: Ambiguous | D91: solar | E91: clarify | F91: P22; P23; P20 | G91: Asks whether they mean the rebate, bill credits, or GreenChoice | I91: new
A92: T091 | B92: EV Programs | C92: Clean paraphrase | D92: is there a rebate for a home ev charger | E92: answer | F92: P24 | G92: 50% of cost up to $500; must enroll in Power Partner EV | I92: new
A93: T092 | B93: EV Programs | C93: Typos / slang | D93: ev chargr rebate how much | E93: answer | F93: P24 | G93: Up to $500 (50% of cost) | I93: new
A94: T093 | B94: EV Programs | C94: Clean paraphrase | D94: whats the cheapest time to charge my car | E94: answer | F94: P25 | G94: Charge between 10 p.m. and 6 a.m.; avoid 4 to 7 p.m. | I94: new
A95: T094 | B95: EV Programs | C95: Spanish | D95: dónde puedo cargar mi carro eléctrico en austin | E95: answer | F95: P25 | G95: Plug-In EVerywhere network; 1,400+ public Level 2 ports | I95: new
A96: T095 | B96: EV Programs | C96: Clean paraphrase | D96: what is power partner ev | E96: answer | F96: P43 | G96: Austin Energy slows or delays charging during peak events; $50 enrollment credit; can opt out | I96: new
A97: T096 | B97: Start/Stop/Transfer Service | C97: Transactional | D97: im moving out and need to shut off my electricity | E97: route | F97: P26 | G97: Call 512-494-9400, Online Customer Care, or a walk in center | I97: new
A98: T097 | B98: Start/Stop/Transfer Service | C98: Transactional | D98: start electric service at my new apartment | E98: route | F98: P26; P27 | G98: Call 512-494-9400 or Online Customer Care; $20 start fee and $200 deposit (can be waived) | I98: new
... A101: T100 | B101: Start/Stop/Transfer Service | C101: Transactional | D101: i need to put the power in my name | E101: route | F101: P26; P27 | G101: Start service via 512-494-9400 or Online Customer Care; deposit may apply | I101: new
A102: T101 | B102: Start/Stop/Transfer Service | C102: Ambiguous | D102: im moving | E102: clarify | F102: P26 | G102: Asks whether they need to start, stop, or transfer service | I102: edited | J102: can i move my service to a new address | K102: Was not ambiguous (it clearly asked to transfer)
A103: T102 | B103: Start/Stop/Transfer Service | C103: Clean paraphrase | D103: how do i transfer utilities | E103: answer | F103: P26 | G103: Call 512-494-9400, Online Customer Care, or a walk in center | I103: kept
A104: T103 | B104: Start/Stop/Transfer Service | C104: Typos / slang | D104: movin houses need lights on at new place | E104: answer | F104: P26 | G104: Start or transfer service via 512-494-9400 or Online Customer Care | I104: edited | J104: i'm relocating inside austin | K104: Row type is Typos but query had no typos
A105: T104 | B105: Start/Stop/Transfer Service | C105: Clean paraphrase | D105: do i have to pay a deposit to start service | E105: answer | F105: P27 | G105: $200 deposit for residential service; can be waived (e.g. good payment history, Autopay and eBill) | I105: edited | J105: switch service to my new home | K105: Was a near repeat of T102
A106: T105 | B106: Start/Stop/Transfer Service | C106: Spanish | D106: transferir mi servicio | E106: answer | F106: P26 | G106: Call 512-494-9400, Online Customer Care, or a walk in center | I106: kept
A107: T106 | B107: Scam Awareness | C107: Clean paraphrase | D107: someone called saying theyll cut my power in an hour unless i pay | E107: answer | F107: P29; P10 | G107: Likely a scam; hang up and dial 3-1-1; check account at 512-494-9400 | I107: new
A108: T107 | B108: Scam Awareness | C108: Ambiguous | D108: i got a weird call about my account | E108: clarify | F108: P29 | G108: Asks what the caller wanted; if they demanded payment, hang up and call 3-1-1 | I108: new
A109: T108 | B109: Scam Awareness | C109: Clean paraphrase | D109: they want me to pay my bill with a gift card is that real | E109: answer | F109: P29 | G109: Scam sign (gift card or prepaid card payment); hang up and report to 3-1-1 | I109: new
A110: T109 | B110: Scam Awareness | C110: Clean paraphrase | D110: a guy at my door says hes from austin energy selling solar panels | E110: answer | F110: P29; P04 | G110: Austin Energy does not sell solar door to door; say not interested; report to 3-1-1 | I110: new
A111: T110 | B111: Scam Awareness | C111: Clean paraphrase | D111: how do i know if a rebate offer is legit | E111: answer | F111: P42 | G111: Verify it on the official Austin Energy program website; report suspicious offers | I111: new
A112: T111 | B112: Tree Trimming | C112: Ambiguous | D112: tree branches are touching power lines | E112: clarify | F112: P39; P04 | G112: Asks if lines are down or sparking (then call 512-322-9100); otherwise submit a Tree Trimming Request | I112: kept
A113: T112 | B113: Tree Trimming | C113: Clean paraphrase | D113: can i request tree trimming | E113: answer | F113: P39 | G113: Submit a Tree Trimming Request Form; inspector evaluates within 2 to 4 weeks | I113: kept
A114: T113 | B114: Tree Trimming | C114: Clean paraphrase | D114: who trims trees near utility lines | E114: answer | F114: P28; P39 | G114: Austin Energy Forestry trims trees near power lines; do not trim limbs within 10 feet of lines yourself | I114: kept
A115: T114 | B115: Tree Trimming | C115: Clean paraphrase | D115: dangerous tree near electrical wires | E115: answer | F115: P39 | G115: Do not trim it yourself; submit a Tree Trimming Request; if sparking call 512-322-9100 | I115: kept
A116: T115 | B116: Tree Trimming | C116: Ambiguous | D116: my tree is a problem | E116: clarify | F116: P39 | G116: Asks whether it is near power lines (Austin Energy) or elsewhere (3-1-1) | I116: edited | J116: poda de árboles cerca de líneas eléctricas | K116: Row type is Ambiguous but query was a clear Spanish request
A117: T116 | B117: Safety | C117: Clean paraphrase | D117: what should i do after a storm outage | E117: answer | F117: P34; P45 | G117: Report outage; stay 35 feet from downed lines; generator safety | I117: kept
A118: T117 | B118: Safety | C118: Clean paraphrase | D118: how do i stay safe around damaged power equipment | E118: answer | F118: P31; P35 | G118: Stay at least 35 feet away; call 512-322-9100 | I118: kept
A119: T118 | B119: Safety | C119: Clean paraphrase | D119: is a downed line dangerous even if it isn't sparking | E119: answer | F119: P35; P31 | G119: Yes, treat every downed line as energized; stay 35 feet away; call 512-322-9100 | I119: kept
A120: T119 | B120: Safety | C120: Ambiguous | D120: what should i do its freezing | E120: clarify | F120: P31; P45 | G120: Asks if their power is out or they need cold weather safety tips | I120: edited | J120: safety tips during a power outage | K120: Was not ambiguous
A121: T120 | B121: Safety | C121: Clean paraphrase | D121: how long will my fridge food stay good without power | E121: answer | F121: P45 | G121: A day or two with doors kept shut; when in doubt throw it out | I121: edited | J121: seguridad durante apagones | K121: Row type is Clean paraphrase but query was in Spanish
A122: T121 | B122: Safety | C122: Clean paraphrase | D122: can i run a generator in my garage | E122: answer | F122: P45 | G122: Never run a generator inside the home or garage | I122: new
A123: T122 | B123: Safety | C123: Clean paraphrase | D123: can i plug the fridge into a power strip | E123: answer | F123: P30 | G123: No; plug major appliances directly into a wall outlet | I123: new
...

Sheet Check Counts
A1: Intent group | B1: Target | C1: Rows in sheet
A2: Report Outage | B2: 10 | C2: =COUNTIF('Test Set'!B:B,A2) -> 10
A3: Check Outage Status | B3: 5 | C3: =COUNTIF('Test Set'!B:B,A3) -> 5
A4: Outage Alerts | B4: 5 | C4: =COUNTIF('Test Set'!B:B,A4) -> 5
A5: Downed Power Lines | B5: 5 | C5: =COUNTIF('Test Set'!B:B,A5) -> 5
A6: Understand My Bill | B6: 10 | C6: =COUNTIF('Test Set'!B:B,A6) -> 10
A7: Payment Options | B7: 5 | C7: =COUNTIF('Test Set'!B:B,A7) -> 5
A8: Payment Arrangement | B8: 5 | C8: =COUNTIF('Test Set'!B:B,A8) -> 5
A9: Collections | B9: 5 | C9: =COUNTIF('Test Set'!B:B,A9) -> 5
A10: Bill Dispute | B10: 5 | C10: =COUNTIF('Test Set'!B:B,A10) -> 5
A11: CAP | B11: 10 | C11: =COUNTIF('Test Set'!B:B,A11) -> 10
A12: Weatherization | B12: 5 | C12: =COUNTIF('Test Set'!B:B,A12) -> 5
A13: Rebates | B13: 10 | C13: =COUNTIF('Test Set'!B:B,A13) -> 10
... A21: Out-of-Scope | B21: 25 | C21: =COUNTIF('Test Set'!B:B,A21) -> 25
A23: Query type | B23: Target | C23: Rows in sheet
A24: Clean paraphrase | B24: 60 | C24: =COUNTIF('Test Set'!C:C,A24) -> 60
A25: Out-of-scope | B25: 25 | C25: =COUNTIF('Test Set'!C:C,A25) -> 25
A26: Ambiguous | B26: 20 | C26: =COUNTIF('Test Set'!C:C,A26) -> 20
A27: Typos / slang | B27: 15 | C27: =COUNTIF('Test Set'!C:C,A27) -> 15
A28: Transactional | B28: 15 | C28: =COUNTIF('Test Set'!C:C,A28) -> 15
A29: Spanish | B29: 15 | C29: =COUNTIF('Test Set'!C:C,A29) -> 15
A31: Queries written | B31: 150 | C31: =COUNTA('Test Set'!D2:D151) -> 150
